kpcli/__init__.py
kpcli/cli.py
kpcli/comparator.py
kpcli/connector.py
kpcli/datastructures.py
kpcli/utils.py
kpcli-0.5.0.dist-info/LICENSE
kpcli-0.5.0.dist-info/METADATA
kpcli-0.5.0.dist-info/WHEEL
kpcli-0.5.0.dist-info/entry_points.txt
kpcli-0.5.0.dist-info/RECORD
