Metadata-Version: 2.1
Name: kpcli
Version: 0.5.0
Summary: A simple command line tool to interact with KeePassX databases
License: GPL-3.0-or-later
Author: Becky Smith
Author-email: rebkwok@gmail.com
Requires-Python: >=3.8
Classifier: License :: OSI Approved :: GNU General Public License v3 or later (GPLv3+)
Classifier: Programming Language :: Python :: 3
Classifier: Programming Language :: Python :: 3.8
Classifier: Programming Language :: Python :: 3.9
Classifier: Programming Language :: Python :: 3.10
Classifier: Programming Language :: Python :: 3.11
Requires-Dist: attrs (>=22.2.0,<23.2)
Requires-Dist: cryptography (>=39.0.1,<41.1)
Requires-Dist: pykeepass (>=4.0.3,<4.1)
Requires-Dist: pyperclip (>=1.8.1,<2.0.0)
Requires-Dist: tableformatter (>=0.1.6,<0.2.0)
Requires-Dist: typer[all] (>=0.7.0,<0.10)
